{"type":"module","coordinates":{"identifier":"com.github.ajalt:mordant","resolvedVersion":"1.2.1","gradleVariantIdentification":{"capabilities":["com.github.ajalt:mordant"],"attributes":{}}},"capabilities":{"com.autonomousapps.model.InferredCapability":{"type":"inferred","isCompileOnlyAnnotations":false},"com.autonomousapps.model.ClassCapability":{"type":"class","classes":["com.github.ajalt.mordant.Ansi16ColorCode","com.github.ajalt.mordant.Ansi256ColorCode","com.github.ajalt.mordant.AnsiCode","com.github.ajalt.mordant.AnsiCode$nest$1","com.github.ajalt.mordant.AnsiCode$nest$1$codes$1","com.github.ajalt.mordant.AnsiColorCode","com.github.ajalt.mordant.AnsiColorsKt","com.github.ajalt.mordant.AnsiRGBColorCode","com.github.ajalt.mordant.DisabledAnsiCode","com.github.ajalt.mordant.DisabledAnsiColorCode","com.github.ajalt.mordant.TermColors","com.github.ajalt.mordant.TermColors$Level","com.github.ajalt.mordant.TermColors$WhenMappings","com.github.ajalt.mordant.TerminalCapabilities"]},"com.autonomousapps.model.ConstantCapability":{"type":"const","constants":{"com.github.ajalt.mordant.AnsiColorsKt":["ESC","CSI","ansiCloseRe"],"com.github.ajalt.mordant.DisabledAnsiCode":["INSTANCE"],"com.github.ajalt.mordant.DisabledAnsiColorCode":["INSTANCE"],"com.github.ajalt.mordant.TermColors$Level":["NONE","ANSI16","ANSI256","TRUECOLOR","$VALUES"],"com.github.ajalt.mordant.TermColors$WhenMappings":["$EnumSwitchMapping$0"],"com.github.ajalt.mordant.TerminalCapabilities":["INSTANCE"]},"ktFiles":[{"fqcn":"com.github.ajalt.mordant.AnsiColorsKt","name":"AnsiColorsKt"}]}},"files":["/Users/jordanterry/.gradle/caches/modules-2/files-2.1/com.github.ajalt/mordant/1.2.1/6cbab1a74ab6dafbf81b7706733d4c2fbaff2e0b/mordant-1.2.1.jar"]}