{"type":"module","coordinates":{"identifier":"androidx.customview:customview","resolvedVersion":"1.0.0","gradleVariantIdentification":{"capabilities":["androidx.customview:customview"],"attributes":{}}},"capabilities":{"com.autonomousapps.model.InferredCapability":{"type":"inferred","isCompileOnlyAnnotations":false},"com.autonomousapps.model.ClassCapability":{"type":"class","classes":["androidx.customview.R","androidx.customview.R$attr","androidx.customview.R$color","androidx.customview.R$dimen","androidx.customview.R$drawable","androidx.customview.R$id","androidx.customview.R$integer","androidx.customview.R$layout","androidx.customview.R$string","androidx.customview.R$style","androidx.customview.R$styleable","androidx.customview.view.AbsSavedState","androidx.customview.view.AbsSavedState$1","androidx.customview.view.AbsSavedState$2","androidx.customview.widget.ExploreByTouchHelper","androidx.customview.widget.ExploreByTouchHelper$1","androidx.customview.widget.ExploreByTouchHelper$2","androidx.customview.widget.ExploreByTouchHelper$MyNodeProvider","androidx.customview.widget.FocusStrategy","androidx.customview.widget.FocusStrategy$BoundsAdapter","androidx.customview.widget.FocusStrategy$CollectionAdapter","androidx.customview.widget.FocusStrategy$SequentialComparator","androidx.customview.widget.ViewDragHelper","androidx.customview.widget.ViewDragHelper$1","androidx.customview.widget.ViewDragHelper$2","androidx.customview.widget.ViewDragHelper$Callback"]},"com.autonomousapps.model.ConstantCapability":{"type":"const","constants":{"androidx.customview.view.AbsSavedState":["EMPTY_STATE","CREATOR"],"androidx.customview.widget.ExploreByTouchHelper":["INVALID_ID","HOST_ID","DEFAULT_CLASS_NAME","INVALID_PARENT_BOUNDS","NODE_ADAPTER","SPARSE_VALUES_ADAPTER"],"androidx.customview.widget.ViewDragHelper":["TAG","INVALID_POINTER","STATE_IDLE","STATE_DRAGGING","STATE_SETTLING","EDGE_LEFT","EDGE_RIGHT","EDGE_TOP","EDGE_BOTTOM","EDGE_ALL","DIRECTION_HORIZONTAL","DIRECTION_VERTICAL","DIRECTION_ALL","EDGE_SIZE","BASE_SETTLE_DURATION","MAX_SETTLE_DURATION","sInterpolator"]},"ktFiles":[]},"com.autonomousapps.model.AndroidManifestCapability":{"type":"manifest","componentMap":{}},"com.autonomousapps.model.AndroidResCapability":{"type":"res","rImport":"androidx.customview.R","lines":[{"type":"color","value":"notification_action_color_filter"},{"type":"color","value":"notification_icon_bg_color"},{"type":"color","value":"ripple_material_light"},{"type":"color","value":"secondary_text_default_material_light"},{"type":"dimen","value":"compat_button_inset_horizontal_material"},{"type":"dimen","value":"compat_button_inset_vertical_material"},{"type":"dimen","value":"compat_button_padding_horizontal_material"},{"type":"dimen","value":"compat_button_padding_vertical_material"},{"type":"dimen","value":"compat_control_corner_material"},{"type":"dimen","value":"compat_notification_large_icon_max_height"},{"type":"dimen","value":"compat_notification_large_icon_max_width"},{"type":"dimen","value":"notification_action_icon_size"},{"type":"dimen","value":"notification_action_text_size"},{"type":"dimen","value":"notification_big_circle_margin"},{"type":"dimen","value":"notification_content_margin_start"},{"type":"dimen","value":"notification_large_icon_height"},{"type":"dimen","value":"notification_large_icon_width"},{"type":"dimen","value":"notification_main_column_padding_top"},{"type":"dimen","value":"notification_media_narrow_margin"},{"type":"dimen","value":"notification_right_icon_size"},{"type":"dimen","value":"notification_right_side_padding_top"},{"type":"dimen","value":"notification_small_icon_background_padding"},{"type":"dimen","value":"notification_small_icon_size_as_large"},{"type":"dimen","value":"notification_subtext_size"},{"type":"dimen","value":"notification_top_pad"},{"type":"dimen","value":"notification_top_pad_large_text"},{"type":"drawable","value":"notification_action_background"},{"type":"drawable","value":"notification_bg"},{"type":"drawable","value":"notification_bg_low"},{"type":"drawable","value":"notification_bg_low_normal"},{"type":"drawable","value":"notification_bg_low_pressed"},{"type":"drawable","value":"notification_bg_normal"},{"type":"drawable","value":"notification_bg_normal_pressed"},{"type":"drawable","value":"notification_icon_background"},{"type":"drawable","value":"notification_template_icon_bg"},{"type":"drawable","value":"notification_template_icon_low_bg"},{"type":"drawable","value":"notification_tile_bg"},{"type":"drawable","value":"notify_panel_notification_icon_bg"},{"type":"id","value":"action_container"},{"type":"id","value":"action_divider"},{"type":"id","value":"action_image"},{"type":"id","value":"action_text"},{"type":"id","value":"actions"},{"type":"id","value":"async"},{"type":"id","value":"blocking"},{"type":"id","value":"chronometer"},{"type":"id","value":"forever"},{"type":"id","value":"icon"},{"type":"id","value":"icon_group"},{"type":"id","value":"info"},{"type":"id","value":"italic"},{"type":"id","value":"line1"},{"type":"id","value":"line3"},{"type":"id","value":"normal"},{"type":"id","value":"notification_background"},{"type":"id","value":"notification_main_column"},{"type":"id","value":"notification_main_column_container"},{"type":"id","value":"right_icon"},{"type":"id","value":"right_side"},{"type":"id","value":"tag_transition_group"},{"type":"id","value":"tag_unhandled_key_event_manager"},{"type":"id","value":"tag_unhandled_key_listeners"},{"type":"id","value":"text"},{"type":"id","value":"text2"},{"type":"id","value":"time"},{"type":"id","value":"title"},{"type":"integer","value":"status_bar_notification_info_maxnum"},{"type":"layout","value":"notification_action"},{"type":"layout","value":"notification_action_tombstone"},{"type":"layout","value":"notification_template_custom_big"},{"type":"layout","value":"notification_template_icon_group"},{"type":"layout","value":"notification_template_part_chronometer"},{"type":"layout","value":"notification_template_part_time"},{"type":"string","value":"status_bar_notification_info_overflow"},{"type":"style","value":"TextAppearance_Compat_Notification"},{"type":"style","value":"Widget_Compat_NotificationActionContainer"},{"type":"style","value":"Widget_Compat_NotificationActionText"}]}},"files":["/Users/jordanterry/.gradle/caches/8.9/transforms/0725a855d3416f90919883b0a9d1bca0/transformed/customview-1.0.0-api.jar"]}